pyCLINE/__init__.py
pyCLINE/example.py
pyCLINE/generate_data.py
pyCLINE/model.py
pyCLINE/recovery_methods/__init__.py
pyCLINE/recovery_methods/data_preparation.py
pyCLINE/recovery_methods/nn_training.py
pycline-0.1.12.dist-info/licenses/LICENSE
pycline-0.1.12.dist-info/METADATA
pycline-0.1.12.dist-info/WHEEL
pycline-0.1.12.dist-info/top_level.txt
pycline-0.1.12.dist-info/RECORD
