Metadata-Version: 2.4
Name: pyCLINE
Version: 0.1.12
Summary: This package is the Python implementation of the CLINE method
Author-email: Bartosz Prokop <bartosz.prokop@kuleuven.be>, Nikita Frolov <nikita.frolov@kuleuven.be>, Lendert Gelens <lendert.gelens@kuleuven.be>
Project-URL: Homepage, https://pycline-ec8369.pages.gitlab.kuleuven.be/
Project-URL: Issues, https://gitlab.kuleuven.be/gelenslab/publications/pycline/-/issues
Keywords: model,model identification,nullcline,data-driven,machine learning,deep learning,torch,dynamics,oscillator,nonlinear dynamics,complex systems
Classifier: Development Status :: 3 - Alpha
Classifier: Programming Language :: Python :: 3
Classifier: Operating System :: OS Independent
Requires-Python: <3.12,>=3.10
License-File: LICENSE
Requires-Dist: matplotlib>=3.6.2
Requires-Dist: numpy<1.25.0,>=1.24.1
Requires-Dist: pandas~=1.5.2
Requires-Dist: torch>=2.4.1
Requires-Dist: tqdm>=4.66.1
Requires-Dist: jitcdde>=1.8.1
Requires-Dist: scipy>=1.9.3
Dynamic: license-file
